<?xml version="1.0" encoding="UTF-8"?><magicdraw><enumerationliteral classType="EnumerationLiteral" humanType="Enumeration Literal" icon="diagrams_files/icon_enumerationliteral_1914441092.png" id="_12_0_f720368_1163257168026_946547_916"><classifier humanName="Classifier"><enumeration classType="Enumeration" humanType="Enumeration" icon="diagrams_files/icon_enumeration_634156144.png" name="MessageKind" refid="_12_0_f720368_1163257109948_937978_912"/></classifier><documentation humanName="Documentation"/><enumeration classType="Enumeration" humanName="Enumeration" humanType="Enumeration" icon="diagrams_files/icon_enumeration_634156144.png" name="MessageKind" refid="_12_0_f720368_1163257109948_937978_912"/><name humanName="Name" mode="s,e">found</name><namespace classType="Enumeration" humanName="Namespace" humanType="Enumeration" icon="diagrams_files/icon_enumeration_634156144.png" name="MessageKind" refid="_12_0_f720368_1163257109948_937978_912"/><owner classType="Enumeration" humanName="Owner" humanType="Enumeration" icon="diagrams_files/icon_enumeration_634156144.png" mode="s,e" name="MessageKind" refid="_12_0_f720368_1163257109948_937978_912"/><qualifiedName humanName="Qualified Name" mode="e">UML Standard Profile::UML2 Metamodel::MessageKind::found</qualifiedName><TO_DO humanName="To Do" mode="s,e"/><visibility humanName="Visibility">public</visibility></enumerationliteral></magicdraw>