<?xml version="1.0" encoding="UTF-8"?><magicdraw><literalboolean classType="LiteralBoolean" humanType="Literal Boolean" icon="diagrams_files/icon_literalboolean_848128374.png" id="_16_8beta_9020291_1261404345621_248843_1118"><documentation humanName="Documentation"/><name humanName="Name"/><owner classType="Property" humanName="Owner" humanType="Property" icon="diagrams_files/icon_property_468125573.png" mode="e" name="isInitialized" refid="_16_8beta_9020291_1261404325436_538645_1109"/><owningProperty classType="Property" humanName="Owning Property" humanType="Property" icon="diagrams_files/icon_property_468125573.png" name="isInitialized" refid="_16_8beta_9020291_1261404325436_538645_1109"/><qualifiedName humanName="Qualified Name">UML Standard Profile::MagicDraw Profile::RelationMap::isInitialized::</qualifiedName><text humanName="Text" mode="standard">true</text><TO_DO humanName="To Do"/><TYPE_MODIFIER humanName="Type Modifier"/><value humanName="Value" mode="s,e">true</value><visibility humanName="Visibility">public</visibility></literalboolean></magicdraw>