<?xml version="1.0" encoding="UTF-8"?><magicdraw><literalinteger classType="LiteralInteger" humanType="Literal Integer" icon="diagrams_files/icon_literalinteger_1620562652.png" id="_17_0_3beta_8e10289_1348753189249_953212_2929"><documentation humanName="Documentation"/><name humanName="Name"/><owner classType="Property" humanName="Owner" humanType="Property" icon="diagrams_files/icon_property_468125573.png" mode="e" name="showInnerDependencies" refid="_17_0_3beta_8e10289_1348753189308_306094_3073"/><owningLower classType="Property" humanName="Owning Lower" humanType="Property" icon="diagrams_files/icon_property_468125573.png" name="showInnerDependencies" refid="_17_0_3beta_8e10289_1348753189308_306094_3073"/><qualifiedName humanName="Qualified Name">UML Standard Profile::Dependency Matrix Profile::DependencyMatrix::showInnerDependencies::</qualifiedName><text humanName="Text" mode="standard">1</text><TO_DO humanName="To Do"/><TYPE_MODIFIER humanName="Type Modifier"/><value humanName="Value" mode="s,e">1</value><visibility humanName="Visibility">public</visibility></literalinteger></magicdraw>