<?xml version="1.0" encoding="UTF-8"?><magicdraw><literalinteger classType="LiteralInteger" humanType="Literal Integer" icon="diagrams_files/icon_literalinteger_1620562652.png" id="_17_0_8f90291_1289574801458_980297_1491"><documentation humanName="Documentation"/><name humanName="Name"/><owner classType="Property" humanName="Owner" humanType="Derived Property Specification" icon="diagrams_files/icon_derivedpropertyspecification_468125573.png" mode="e" name="specifyingComponent" refid="_17_0_8f90291_1289574801458_57348_1486"/><owningLower classType="Property" humanName="Owning Lower" humanType="Derived Property Specification" icon="diagrams_files/icon_derivedpropertyspecification_468125573.png" name="specifyingComponent" refid="_17_0_8f90291_1289574801458_57348_1486"/><qualifiedName humanName="Qualified Name">UML Standard Profile::MagicDraw Profile::Traceability customization::Properties descriptors::Specification::Classifier Specifying Components::specifyingComponent::</qualifiedName><text humanName="Text" mode="standard">0</text><TO_DO humanName="To Do"/><TYPE_MODIFIER humanName="Type Modifier"/><value humanName="Value" mode="s,e">0</value><visibility humanName="Visibility">public</visibility></literalinteger></magicdraw>