<?xml version="1.0" encoding="UTF-8"?><magicdraw><literalstring classType="LiteralString" humanType="Literal String" icon="diagrams_files/icon_literalstring_1932546331.png" id="_18_5_3_43701b0_1515708287457_946749_4868"><documentation humanName="Documentation"/><name humanName="Name"/><owner classType="Slot" humanName="Owner" humanType="Slot" icon="diagrams_files/icon_slot_186568829.png" mode="e" refid="_18_5_3_43701b0_1515708287457_355539_4867"/><owningSlot classType="Slot" humanName="Owning Slot" humanType="Slot" icon="diagrams_files/icon_slot_186568829.png" refid="_18_5_3_43701b0_1515708287457_355539_4867"/><qualifiedName humanName="Qualified Name"/><text humanName="Text" mode="standard">USE</text><TO_DO humanName="To Do"/><TYPE_MODIFIER humanName="Type Modifier"/><value humanName="Value" mode="s,e">USE</value><visibility humanName="Visibility">public</visibility></literalstring></magicdraw>