<?xml version="1.0" encoding="UTF-8"?><magicdraw><instancespecification classType="InstanceSpecification" humanType="Instance Specification" icon="diagrams_files/icon_instancespecification_719182854.png" id="_18_5_3_43701b0_1522260279617_173737_22157"><classifier humanName="Classifier" mode="s,e"><stereotype classType="Stereotype" humanType="Stereotype" icon="diagrams_files/icon_stereotype_123674777.png" name="Resource" refid="_18_0_1_8bf027c_1408661908824_320374_5622"/><stereotype classType="Stereotype" humanType="Stereotype" icon="diagrams_files/icon_stereotype_123674777.png" name="Union" refid="_18_0_1_8bf027c_1409322510396_866557_6932"/></classifier><documentation humanName="Documentation"/><name humanName="Name" mode="s,e"/><owner classType="Class" humanName="Owner" humanType="Class" icon="diagrams_files/icon_class_1932244589.png" mode="s,e" name="Voter Party Affiliation Methods" refid="_18_5_3_43701b0_1522260279617_50907_22156"/><qualifiedName humanName="Qualified Name" mode="e">Elections::Voter Party Affiliation Methods::</qualifiedName><stereotypedElement classType="Class" humanName="Stereotyped Element" humanType="Class" icon="diagrams_files/icon_class_1932244589.png" name="Voter Party Affiliation Methods" refid="_18_5_3_43701b0_1522260279617_50907_22156"/><TO_DO humanName="To Do" mode="s,e"/><visibility humanName="Visibility">public</visibility></instancespecification></magicdraw>