<?xml version="1.0" encoding="UTF-8"?><magicdraw><region classType="Region" humanType="Region" icon="diagrams_files/icon_region_1579943881.png" id="_18_5_3_43701b0_1535581789124_949600_38564"><documentation humanName="Documentation"/><isLeaf humanName="Is Leaf">false</isLeaf><member humanName="Member"><state classType="State" humanType="State" icon="diagrams_files/icon_state_1958873486.png" name="Read Ballot" refid="_18_5_3_43701b0_1535562460574_696398_22786"/><transition classType="Transition" humanType="Transition" icon="diagrams_files/icon_transition_213683471.png" isRelationship="true" name="Transition:Record [Provisional][Ballot Marking States::thing::Issued::::Cast Ballot::::::::Read Ballot -&gt; Ballot Marking States::thing::Issued::::Cast Ballot::::::::Read Ballot::::Recallable Ballot]" refid="_18_5_3_43701b0_1535562709191_188238_23448"/><transition classType="Transition" humanType="Transition" icon="diagrams_files/icon_transition_213683471.png" isRelationship="true" name="Transition:Record [Successful][Ballot Marking States::thing::Issued::::Cast Ballot::::::::Read Ballot -&gt; Ballot Marking States::thing::Issued::::Cast Ballot::::::::Read Ballot::::Recorded Ballot]" refid="_18_5_3_43701b0_1535562640701_811174_23439"/></member><name humanName="Name" mode="s,e"/><namespace classType="State" humanName="Namespace" humanType="State" icon="diagrams_files/icon_state_1958873486.png" name="" refid="_18_5_3_43701b0_1535581789124_515_38563"/><ownedElement humanName="Owned Element"><state classType="State" humanType="State" icon="diagrams_files/icon_state_1958873486.png" name="Read Ballot" refid="_18_5_3_43701b0_1535562460574_696398_22786"/><transition classType="Transition" humanType="Transition" icon="diagrams_files/icon_transition_213683471.png" isRelationship="true" name="Transition:Record [Provisional][Ballot Marking States::thing::Issued::::Cast Ballot::::::::Read Ballot -&gt; Ballot Marking States::thing::Issued::::Cast Ballot::::::::Read Ballot::::Recallable Ballot]" refid="_18_5_3_43701b0_1535562709191_188238_23448"/><transition classType="Transition" humanType="Transition" icon="diagrams_files/icon_transition_213683471.png" isRelationship="true" name="Transition:Record [Successful][Ballot Marking States::thing::Issued::::Cast Ballot::::::::Read Ballot -&gt; Ballot Marking States::thing::Issued::::Cast Ballot::::::::Read Ballot::::Recorded Ballot]" refid="_18_5_3_43701b0_1535562640701_811174_23439"/></ownedElement><ownedMember humanName="Owned Member"><state classType="State" humanType="State" icon="diagrams_files/icon_state_1958873486.png" name="Read Ballot" refid="_18_5_3_43701b0_1535562460574_696398_22786"/><transition classType="Transition" humanType="Transition" icon="diagrams_files/icon_transition_213683471.png" isRelationship="true" name="Transition:Record [Provisional][Ballot Marking States::thing::Issued::::Cast Ballot::::::::Read Ballot -&gt; Ballot Marking States::thing::Issued::::Cast Ballot::::::::Read Ballot::::Recallable Ballot]" refid="_18_5_3_43701b0_1535562709191_188238_23448"/><transition classType="Transition" humanType="Transition" icon="diagrams_files/icon_transition_213683471.png" isRelationship="true" name="Transition:Record [Successful][Ballot Marking States::thing::Issued::::Cast Ballot::::::::Read Ballot -&gt; Ballot Marking States::thing::Issued::::Cast Ballot::::::::Read Ballot::::Recorded Ballot]" refid="_18_5_3_43701b0_1535562640701_811174_23439"/></ownedMember><owner classType="State" humanName="Owner" humanType="State" icon="diagrams_files/icon_state_1958873486.png" mode="s,e" name="" refid="_18_5_3_43701b0_1535581789124_515_38563"/><qualifiedName humanName="Qualified Name" mode="e">Ballot Marking States::thing::Issued::::Cast Ballot::::::</qualifiedName><state classType="State" humanName="State" humanType="State" icon="diagrams_files/icon_state_1958873486.png" name="" refid="_18_5_3_43701b0_1535581789124_515_38563"/><subvertex humanName="Subvertex"><state classType="State" humanType="State" icon="diagrams_files/icon_state_1958873486.png" name="Read Ballot" refid="_18_5_3_43701b0_1535562460574_696398_22786"/></subvertex><TO_DO humanName="To Do" mode="s,e"/><transition humanName="Transition"><transition classType="Transition" humanType="Transition" icon="diagrams_files/icon_transition_213683471.png" isRelationship="true" name="Transition:Record [Provisional][Ballot Marking States::thing::Issued::::Cast Ballot::::::::Read Ballot -&gt; Ballot Marking States::thing::Issued::::Cast Ballot::::::::Read Ballot::::Recallable Ballot]" refid="_18_5_3_43701b0_1535562709191_188238_23448"/><transition classType="Transition" humanType="Transition" icon="diagrams_files/icon_transition_213683471.png" isRelationship="true" name="Transition:Record [Successful][Ballot Marking States::thing::Issued::::Cast Ballot::::::::Read Ballot -&gt; Ballot Marking States::thing::Issued::::Cast Ballot::::::::Read Ballot::::Recorded Ballot]" refid="_18_5_3_43701b0_1535562640701_811174_23439"/></transition><visibility humanName="Visibility">public</visibility><appearsIn><diagram classType="Diagram" humanType="Diagram" icon="diagrams_files/icon_State Machine Diagram_1244165469.png" name="Ballot Marking States" refid="_18_5_3_43701b0_1524070193369_815521_30248"/></appearsIn></region></magicdraw>