<?xml version="1.0" encoding="UTF-8"?><magicdraw><trigger classType="Trigger" humanType="Trigger" icon="diagrams_files/icon_trigger_151197067.png" id="_18_5_3_43701b0_1527112687955_909660_20302"><documentation humanName="Documentation"/><event classType="SignalEvent" humanName="Event" humanType="Signal Event" icon="diagrams_files/icon_signalevent_901041395.png" name="Void1" refid="_18_5_3_43701b0_1527112687962_837118_20325"/><eventType humanName="Event Type" mode="s,e">SignalEvent</eventType><name humanName="Name" mode="s,e"/><owner classType="Transition" humanName="Owner" humanType="Transition" icon="diagrams_files/icon_transition_463215441.png" isRelationship="true" mode="s,e" name="Transition:Void1[Marked Ballot -&gt; Void Ballot]" refid="_18_5_3_43701b0_1527112687946_223979_20279"/><qualifiedName humanName="Qualified Name">Data::::::</qualifiedName><TO_DO humanName="To Do"/><visibility humanName="Visibility">public</visibility></trigger></magicdraw>