<?xml version="1.0" encoding="UTF-8"?><magicdraw><elementvalue classType="ElementValue" humanType="Element Value" icon="diagrams_files/icon_elementvalue_1365843285.png" id="_18_5_3_43701b0_1528898406873_253697_8571"><documentation humanName="Documentation"/><element classType="Property" humanName="Element" humanType="Property" icon="diagrams_files/icon_property_2066461130.png" mode="s,e" name="has election supervisor" refid="_18_5_3_43701b0_1516029640525_992732_13022"/><name humanName="Name"/><owner classType="Slot" humanName="Owner" humanType="Slot" icon="diagrams_files/icon_slot_973461775.png" mode="e" refid="_18_5_3_43701b0_1528898406866_434777_8467"/><owningSlot classType="Slot" humanName="Owning Slot" humanType="Slot" icon="diagrams_files/icon_slot_973461775.png" refid="_18_5_3_43701b0_1528898406866_434777_8467"/><qualifiedName humanName="Qualified Name"/><text humanName="Text" mode="standard">has election supervisor</text><TO_DO humanName="To Do"/><TYPE_MODIFIER humanName="Type Modifier"/><visibility humanName="Visibility">public</visibility></elementvalue></magicdraw>