<?xml version="1.0" encoding="UTF-8"?><magicdraw><property classType="Property" humanType="Property" icon="diagrams_files/icon_property_1938930866.png" id="_18_5_3_43701b0_1523477490236_964892_21231"><aggregation humanName="Aggregation" mode="s,e">none</aggregation><association classType="Association" humanName="Association" humanType="Association" icon="diagrams_files/icon_association_2035369567.png" isRelationship="true" name="Association[Elections::Partisan Ballot -&gt; has party:Elections::Party]" refid="_18_5_3_43701b0_1523477490236_868153_21229"/><documentation humanName="Documentation"/><effectiveIRI humanName="Effective IRI" mode="s,e">http://www.semanticweb.org/jdziu_000/ontologies/2017/5/elections#</effectiveIRI><featuringClassifier classType="Association" humanName="Featuring Classifier" humanType="Association" icon="diagrams_files/icon_association_2035369567.png" isRelationship="true" name="Association[Elections::Partisan Ballot -&gt; has party:Elections::Party]" refid="_18_5_3_43701b0_1523477490236_868153_21229"/><isComposite humanName="Is Composite">false</isComposite><isDerived humanName="Is Derived" mode="s,e">false</isDerived><isDerivedUnion humanName="Is Derived Union" mode="e">false</isDerivedUnion><isID humanName="Is ID" mode="e">false</isID><isLeaf humanName="Is Leaf">false</isLeaf><isOrdered humanName="Is Ordered" mode="e">false</isOrdered><isReadOnly humanName="Is Read Only" mode="s,e">false</isReadOnly><isStatic humanName="Is Static" mode="s,e">false</isStatic><isUnique humanName="Is Unique" mode="e">true</isUnique><lower humanName="Lower">1</lower><multiplicity humanName="Multiplicity" mode="s,e"/><name humanName="Name" mode="s,e"/><namespace classType="Association" humanName="Namespace" humanType="Association" icon="diagrams_files/icon_association_2035369567.png" isRelationship="true" name="Association[Elections::Partisan Ballot -&gt; has party:Elections::Party]" refid="_18_5_3_43701b0_1523477490236_868153_21229"/><navigable humanName="Navigable" mode="e">false</navigable><opposite classType="Property" humanName="Opposite" humanType="Property" icon="diagrams_files/icon_property_1938930866.png" name="has party" refid="_18_5_3_43701b0_1523477490236_259344_21230"/><ownedBy classType="Association" humanName="Owned By" humanType="Association" icon="diagrams_files/icon_association_2035369567.png" isRelationship="true" mode="s,e" name="Association[Elections::Partisan Ballot -&gt; has party:Elections::Party]" refid="_18_5_3_43701b0_1523477490236_868153_21229"/><owner classType="Association" humanName="Owner" humanType="Association" icon="diagrams_files/icon_association_2035369567.png" isRelationship="true" name="Association[Elections::Partisan Ballot -&gt; has party:Elections::Party]" refid="_18_5_3_43701b0_1523477490236_868153_21229"/><owningAssociation classType="Association" humanName="Owning Association" humanType="Association" icon="diagrams_files/icon_association_2035369567.png" isRelationship="true" name="Association[Elections::Partisan Ballot -&gt; has party:Elections::Party]" refid="_18_5_3_43701b0_1523477490236_868153_21229"/><qualifiedName humanName="Qualified Name" mode="e">Elections::::</qualifiedName><redefinitionContext humanName="Redefinition Context"><association classType="Association" humanType="Association" icon="diagrams_files/icon_association_2035369567.png" isRelationship="true" name="Association[Elections::Partisan Ballot -&gt; has party:Elections::Party]" refid="_18_5_3_43701b0_1523477490236_868153_21229"/></redefinitionContext><TO_DO humanName="To Do" mode="s,e"/><type classType="Class" humanName="Type" humanType="Class" icon="diagrams_files/icon_class_402207819.png" mode="s,e" name="Partisan Ballot" refid="_18_5_3_43701b0_1523477593187_834158_21299"/><TYPE_MODIFIER humanName="Type Modifier" mode="e"/><upper humanName="Upper">1</upper><visibility humanName="Visibility" mode="s,e">public</visibility><appearsIn><diagram classType="Diagram" humanType="Diagram" icon="diagrams_files/icon_Concept Modeling Diagram_1542899851.png" name="Primary" refid="_18_5_3_43701b0_1522877840073_522481_29940"/></appearsIn></property></magicdraw>