<?xml version="1.0" encoding="UTF-8"?><magicdraw><slot classType="Slot" humanType="Slot" icon="diagrams_files/icon_slot_186568829.png" id="_18_5_3_43701b0_1515708287511_718805_5051"><definingFeature classType="Property" humanName="Defining Feature" humanType="Property" icon="diagrams_files/icon_property_468125573.png" mode="s,e" name="errorMessage" refid="_11_5_f720368_1159529753480_546197_91"/><documentation humanName="Documentation"/><ownedElement humanName="Owned Element"><literalstring classType="LiteralString" humanType="Literal String" icon="diagrams_files/icon_literalstring_1932546331.png" name="Too few tagged values for {self.definingFeature.featuringClassifier.name}::{self.definingFeature.name} tag - at least {self.definingFeature.lower} values are required" refid="_18_5_3_43701b0_1515708287511_550720_5052" text="Too few tagged values for {self.definingFeature.featuringClassifier.name}::{self.definingFeature.name} tag - at least {self.definingFeature.lower} values are required"/></ownedElement><owner classType="InstanceSpecification" humanName="Owner" humanType="Instance Specification" icon="diagrams_files/icon_instancespecification_910504711.png" mode="s,e" name=" : UML Standard Profile::MagicDraw Profile::InvisibleStereotype, UML Standard Profile::Validation Profile::validationRule" refid="_16_5beta1_8f90291_1233238272589_355624_833"/><owningInstance classType="InstanceSpecification" humanName="Owning Instance" humanType="Instance Specification" icon="diagrams_files/icon_instancespecification_910504711.png" name=" : UML Standard Profile::MagicDraw Profile::InvisibleStereotype, UML Standard Profile::Validation Profile::validationRule" refid="_16_5beta1_8f90291_1233238272589_355624_833"/><TO_DO humanName="To Do" mode="s,e"/><value humanName="Value" mode="s,e"><literalstring classType="LiteralString" humanType="Literal String" icon="diagrams_files/icon_literalstring_1932546331.png" name="Too few tagged values for {self.definingFeature.featuringClassifier.name}::{self.definingFeature.name} tag - at least {self.definingFeature.lower} values are required" refid="_18_5_3_43701b0_1515708287511_550720_5052" text="Too few tagged values for {self.definingFeature.featuringClassifier.name}::{self.definingFeature.name} tag - at least {self.definingFeature.lower} values are required"/></value></slot></magicdraw>