<?xml version="1.0" encoding="UTF-8"?><magicdraw><elementvalue classType="ElementValue" humanType="Element Value" icon="diagrams_files/icon_elementvalue_55108719.png" id="_19_0_4_43701b0_1614270826263_14171_12870"><documentation humanName="Documentation"/><element classType="Property" humanName="Element" humanType="Property" icon="diagrams_files/icon_property_1548581152.png" mode="s,e" name="definition" refid="_18_5_3_43701b0_1516025334063_937444_7230"/><name humanName="Name"/><owner classType="Slot" humanName="Owner" humanType="Slot" icon="diagrams_files/icon_slot_1423824757.png" mode="e" refid="_19_0_4_43701b0_1614270826263_718936_12869"/><owningSlot classType="Slot" humanName="Owning Slot" humanType="Slot" icon="diagrams_files/icon_slot_1423824757.png" refid="_19_0_4_43701b0_1614270826263_718936_12869"/><qualifiedName humanName="Qualified Name"/><text humanName="Text" mode="standard">definition</text><TO_DO humanName="To Do"/><TYPE_MODIFIER humanName="Type Modifier"/><visibility humanName="Visibility">public</visibility></elementvalue></magicdraw>