<?xml version="1.0" encoding="UTF-8"?><magicdraw><elementvalue classType="ElementValue" humanType="Element Value" icon="diagrams_files/icon_elementvalue_1391861830.png" id="_19_0_43701b0_1536166294720_938881_7760"><documentation humanName="Documentation"/><element classType="Property" humanName="Element" humanType="Property" icon="diagrams_files/icon_property_1938930866.png" mode="s,e" name="has voter" refid="_18_5_3_43701b0_1522878031678_808104_30130"/><name humanName="Name"/><owner classType="Slot" humanName="Owner" humanType="Slot" icon="diagrams_files/icon_slot_139388564.png" mode="e" refid="_19_0_43701b0_1536166294720_650438_7758"/><owningSlot classType="Slot" humanName="Owning Slot" humanType="Slot" icon="diagrams_files/icon_slot_139388564.png" refid="_19_0_43701b0_1536166294720_650438_7758"/><qualifiedName humanName="Qualified Name"/><text humanName="Text" mode="standard">has voter</text><TO_DO humanName="To Do"/><TYPE_MODIFIER humanName="Type Modifier"/><visibility humanName="Visibility">public</visibility></elementvalue></magicdraw>