<?xml version="1.0" encoding="UTF-8"?><magicdraw><elementvalue classType="ElementValue" humanType="Element Value" icon="diagrams_files/icon_elementvalue_1391861830.png" id="_19_0_43701b0_1536166294654_815362_6160"><documentation humanName="Documentation"/><element classType="Property" humanName="Element" humanType="Property" icon="diagrams_files/icon_property_1938930866.png" mode="s,e" name="has affiliating primary" refid="_18_5_3_43701b0_1522866058160_521208_26050"/><name humanName="Name"/><owner classType="Slot" humanName="Owner" humanType="Slot" icon="diagrams_files/icon_slot_139388564.png" mode="e" refid="_19_0_43701b0_1536166294640_921849_5793"/><owningSlot classType="Slot" humanName="Owning Slot" humanType="Slot" icon="diagrams_files/icon_slot_139388564.png" refid="_19_0_43701b0_1536166294640_921849_5793"/><qualifiedName humanName="Qualified Name"/><text humanName="Text" mode="standard">has affiliating primary</text><TO_DO humanName="To Do"/><TYPE_MODIFIER humanName="Type Modifier"/><visibility humanName="Visibility">public</visibility></elementvalue></magicdraw>