<?xml version="1.0" encoding="UTF-8"?><magicdraw><literalunlimitednatural classType="LiteralUnlimitedNatural" humanType="Literal Unlimited Natural" icon="diagrams_files/icon_literalunlimitednatural_506130535.png" id="_19_0_43701b0_1539194768674_500047_18777"><documentation humanName="Documentation"/><name humanName="Name"/><owner classType="Property" humanName="Owner" humanType="Property" icon="diagrams_files/icon_property_1548581152.png" mode="e" name=" : Party Specific Contest [0..*]" refid="_19_0_43701b0_1539194751267_511231_18756"/><owningUpper classType="Property" humanName="Owning Upper" humanType="Property" icon="diagrams_files/icon_property_1548581152.png" name=" : Party Specific Contest [0..*]" refid="_19_0_43701b0_1539194751267_511231_18756"/><qualifiedName humanName="Qualified Name">Elections::Party Specific Narrowing Purpose::::</qualifiedName><text humanName="Text" mode="standard">*</text><TO_DO humanName="To Do"/><TYPE_MODIFIER humanName="Type Modifier"/><value humanName="Value" mode="s,e">-1</value><visibility humanName="Visibility">public</visibility></literalunlimitednatural></magicdraw>