<?xml version="1.0" encoding="UTF-8"?><magicdraw><class classType="Class" humanType="Class" icon="diagrams_files/icon_class_966745694.png" id="_9_0_62a020a_1105704885779_949036_8059"><documentation humanName="Documentation"/><effectiveIRI humanName="Effective IRI" mode="s,e"/><extension humanName="Extension"><extension classType="Extension" humanType="Extension" icon="diagrams_files/icon_extension_1930657514.png" isRelationship="true" name="Extension[base_Usage:UML Standard Profile::StandardProfile::Call - extension_call:UML Standard Profile::UML2 Metamodel::Usage]" refid="_10_0EAPbeta_be00301_1123081772558_497375_370"/><extension classType="Extension" humanType="Extension" icon="diagrams_files/icon_extension_1930657514.png" isRelationship="true" name="Extension[base_Usage:UML Standard Profile::StandardProfile::Create - extension_create:UML Standard Profile::UML2 Metamodel::Usage]" refid="_10_0EAPbeta_be00301_1123081771997_210055_248"/><extension classType="Extension" humanType="Extension" icon="diagrams_files/icon_extension_1930657514.png" isRelationship="true" name="Extension[base_Usage:UML Standard Profile::StandardProfile::Instantiate - extension_instantiate:UML Standard Profile::UML2 Metamodel::Usage]" refid="_10_0EAPbeta_be00301_1123081771547_124683_147"/><extension classType="Extension" humanType="Extension" icon="diagrams_files/icon_extension_1930657514.png" isRelationship="true" name="Extension[base_Usage:UML Standard Profile::StandardProfile::Responsibility - extension_responsibility:UML Standard Profile::UML2 Metamodel::Usage]" refid="_10_0EAPbeta_be00301_1123081771567_444984_152"/><extension classType="Extension" humanType="Extension" icon="diagrams_files/icon_extension_1930657514.png" isRelationship="true" name="Extension[base_Usage:UML Standard Profile::StandardProfile::Send - extension_send:UML Standard Profile::UML2 Metamodel::Usage]" refid="_10_0EAPbeta_be00301_1123081772338_421996_319"/></extension><generalization humanName="Generalization"><generalization classType="Generalization" humanType="Generalization" icon="diagrams_files/icon_generalization_648358364.png" isRelationship="true" refid="_9_0_62a020a_1105704944209_785473_9858"/></generalization><isAbstract humanName="Is Abstract" mode="s,e">false</isAbstract><isActive humanName="Is Active" mode="s,e">false</isActive><isFinalSpecialization humanName="Is Final Specialization" mode="e">false</isFinalSpecialization><isLeaf humanName="Is Leaf" mode="e">false</isLeaf><name humanName="Name" mode="s,e">Usage</name><namespace classType="Model" humanName="Namespace" humanType="Model" icon="diagrams_files/icon_model_951677655.png" name="UML2 Metamodel" refid="_9_0_be00301_1108053761194_467635_11463"/><ownedElement humanName="Owned Element"><generalization classType="Generalization" humanType="Generalization" icon="diagrams_files/icon_generalization_648358364.png" isRelationship="true" refid="_9_0_62a020a_1105704944209_785473_9858"/></ownedElement><owner classType="Model" humanName="Owner" humanType="Model" icon="diagrams_files/icon_model_951677655.png" mode="s,e" name="UML2 Metamodel" refid="_9_0_be00301_1108053761194_467635_11463"/><owningPackage classType="Model" humanName="Owning Package" humanType="Model" icon="diagrams_files/icon_model_951677655.png" name="UML2 Metamodel" refid="_9_0_be00301_1108053761194_467635_11463"/><package classType="Model" humanName="Package" humanType="Model" icon="diagrams_files/icon_model_951677655.png" name="UML2 Metamodel" refid="_9_0_be00301_1108053761194_467635_11463"/><qualifiedName humanName="Qualified Name" mode="e">UML Standard Profile::UML2 Metamodel::Usage</qualifiedName><superClass humanName="Super Class"><class classType="Class" humanType="Class" icon="diagrams_files/icon_class_966745694.png" name="Dependency" refid="_9_0_62a020a_1105704885833_713624_8075"/></superClass><TO_DO humanName="To Do" mode="s,e"/><visibility humanName="Visibility" mode="e">public</visibility></class></magicdraw>