<?xml version="1.0" encoding="UTF-8"?><magicdraw><comment classType="Comment" humanType="Comment" icon="diagrams_files/icon_comment_1105641037.png" id="_9_0_2_be00301_1111680876843_488504_27189"><annotatedElement humanName="Annotated Element" mode="s,e"><stereotype classType="Stereotype" humanType="Stereotype" icon="diagrams_files/icon_stereotype_2041996211.png" name="Implement" refid="rimvydas_1048689091049_622839_0"/></annotatedElement><body humanName="Body" mode="s,e">A component definition that is not intended to have a
specification itself. Rather, it is an implementation for a
separate «specification» to which it has a Dependency.</body><documentation humanName="Documentation"/><owner classType="Stereotype" humanName="Owner" humanType="Stereotype" icon="diagrams_files/icon_stereotype_2041996211.png" mode="s,e" name="Implement" refid="rimvydas_1048689091049_622839_0"/><owningElement classType="Stereotype" humanName="Owning Element" humanType="Stereotype" icon="diagrams_files/icon_stereotype_2041996211.png" name="Implement" refid="rimvydas_1048689091049_622839_0"/><TO_DO humanName="To Do" mode="s,e"/></comment></magicdraw>